tests/__init__.py
tests/download_pytest.py
tests/test_image.py
tests/test_sum.py
uavsar_pytools/__init__.py
uavsar_pytools/georeference.py
uavsar_pytools/incidence_angle.py
uavsar_pytools/polsar.py
uavsar_pytools/snow_depth_inversion.py
uavsar_pytools/uavsar_collection.py
uavsar_pytools/uavsar_image.py
uavsar_pytools/uavsar_scene.py
uavsar_pytools/uavsar_tools.py
uavsar_pytools/convert/file_control.py
uavsar_pytools/convert/tiff_conversion.py
uavsar_pytools/download/download.py
uavsar_pytools-0.7.0.dist-info/METADATA
uavsar_pytools-0.7.0.dist-info/WHEEL
uavsar_pytools-0.7.0.dist-info/top_level.txt
uavsar_pytools-0.7.0.dist-info/RECORD
