Metadata-Version: 2.1
Name: uavsar-pytools
Version: 0.7.0
Summary: Tools to download and convert ground projected UAVSAR images.
Home-page: https://github.com/SnowEx/uavsar_pytools
Author: Zach Keskinen and Jack Tarricone
Author-email: zachkeskinen@gmail.com
License: MIT
Platform: UNKNOWN
Classifier: License :: OSI Approved :: MIT License
Classifier: Programming Language :: Python
Classifier: Programming Language :: Python :: 3
Classifier: Programming Language :: Python :: 3.7
Classifier: Programming Language :: Python :: Implementation :: CPython
Classifier: Programming Language :: Python :: Implementation :: PyPy
Requires-Python: >=3.7.0
Requires-Dist: requests
Requires-Dist: asf-search
Requires-Dist: progressbar
Requires-Dist: tqdm
Requires-Dist: folium
Requires-Dist: geopandas
Requires-Dist: numpy
Requires-Dist: rasterio
Requires-Dist: matplotlib
Requires-Dist: rioxarray
Requires-Dist: dask
